ssh_client/__init__.py
ssh_client/client.py
ssh_client/cmd.py
ssh_client/unix_path.py
ssh_client/zip.py
test/__init__.py
test/test_all.py
ssh_client_baoer-0.0.23.dist-info/METADATA
ssh_client_baoer-0.0.23.dist-info/WHEEL
ssh_client_baoer-0.0.23.dist-info/top_level.txt
ssh_client_baoer-0.0.23.dist-info/RECORD
