Metadata-Version: 2.1
Name: ssh-client-baoer
Version: 0.0.23
Summary: SSH Client.
Home-page: https://gitee.com/haitaoboy/ssh-client
Author: baoer
Author-email: 821832333@qq.com
Classifier: Programming Language :: Python :: 3
Classifier: License :: OSI Approved :: MIT License
Classifier: Operating System :: OS Independent
Requires-Python: >=3.6
Requires-Dist: fabric (==2.6.0)
Requires-Dist: paramiko (==2.7.2)
Requires-Dist: invoke (==1.6.0)
